MANIFEST.in
README.rst
setup.py
django_native_tags.egg-info/PKG-INFO
django_native_tags.egg-info/SOURCES.txt
django_native_tags.egg-info/dependency_links.txt
django_native_tags.egg-info/top_level.txt
native_tags/__init__.py
native_tags/decorators.py
native_tags/models.py
native_tags/nodes.py
native_tags/registry.py
native_tags/settings.py
native_tags/tests.py
native_tags/contrib/LICENSE.txt
native_tags/contrib/__init__.py
native_tags/contrib/_django.py
native_tags/contrib/_markup.py
native_tags/contrib/baseencode.py
native_tags/contrib/cal.py
native_tags/contrib/comparison.py
native_tags/contrib/context.py
native_tags/contrib/feeds.py
native_tags/contrib/gchart.py
native_tags/contrib/generic_content.py
native_tags/contrib/generic_markup.py
native_tags/contrib/hash.py
native_tags/contrib/mapreduce.py
native_tags/contrib/math_.py
native_tags/contrib/op.py
native_tags/contrib/pygmentize.py
native_tags/contrib/rand.py
native_tags/contrib/regex.py
native_tags/contrib/serializers.py
native_tags/management/__init__.py
native_tags/management/commands/__init__.py
native_tags/management/commands/nativelib.py
native_tags/templatetags/__init__.py
native_tags/templatetags/native.py