Metadata-Version: 1.0
Name: django-native-tags
Version: 0.5.3
Summary: Native, Pythonic Templatetags for Django
Home-page: http://github.com/justquick/django-native-tags
Author: Justin Quick
Author-email: justquick@gmail.com
License: UNKNOWN
Platform: UNKNOWN
Classifier: Development Status :: 5 - Production/Stable
Classifier: Environment :: Web Environment
Classifier: Framework :: Django
Classifier: Intended Audience :: Developers
Classifier: License :: OSI Approved :: BSD License
Classifier: Operating System :: OS Independent
Classifier: Programming Language :: Python
Classifier: Topic :: Utilities
